LICENSE
README.md
setup.py
wordpress_scraper/__init__.py
wordpress_scraper.egg-info/PKG-INFO
wordpress_scraper.egg-info/SOURCES.txt
wordpress_scraper.egg-info/dependency_links.txt
wordpress_scraper.egg-info/requires.txt
wordpress_scraper.egg-info/top_level.txt