Metadata-Version: 2.1
Name: wordpress-scraper
Version: 1.0.0
Summary: A python library to scrape wordpress blog
Home-page: UNKNOWN
Author: DataKund
Author-email: datakund@gmail.com
License: Apache License 2.0
Keywords: Wordpress blog python bot_studio automation title description post
Platform: UNKNOWN
License-File: LICENSE
